permissions_manager/__init__.py
permissions_manager/permissions_manager.py
tests/__init__.py
tests/test_permissions_manager.py
env_permissions_manager-0.0.1.dist-info/METADATA
env_permissions_manager-0.0.1.dist-info/WHEEL
env_permissions_manager-0.0.1.dist-info/top_level.txt
env_permissions_manager-0.0.1.dist-info/RECORD
