Metadata-Version: 2.1
Name: env-permissions-manager
Version: 0.0.1
Summary: A Python package to manage permissions of Python environments
Author: Karim Baidar
Author-email: karimbaidar@gmail.com
Classifier: Development Status :: 3 - Alpha
Classifier: Intended Audience :: Developers
Classifier: License :: OSI Approved :: MIT License
Classifier: Programming Language :: Python :: 3.6
Requires-Dist: numpy
Requires-Dist: requests
Requires-Dist: pytest
Requires-Dist: setuptools
Requires-Dist: urllib3
Requires-Dist: pip
